geospatialtools/__init__.py
geospatialtools/children.py
geospatialtools/common.py
geospatialtools/contraction.py
geospatialtools/jupyter.py
geospatialtools/poi.py
geospatialtools/problem.py
geospatialtools/search.py
geospatialtools/viz.py
geospatialtools-1.0.0.dist-info/LICENSE
geospatialtools-1.0.0.dist-info/METADATA
geospatialtools-1.0.0.dist-info/WHEEL
geospatialtools-1.0.0.dist-info/top_level.txt
geospatialtools-1.0.0.dist-info/RECORD
